henge/__init__.py
henge/_version.py
henge/const.py
henge/deprecated.py
henge/henge.py
henge-0.2.2.dist-info/LICENSE.txt
henge-0.2.2.dist-info/METADATA
henge-0.2.2.dist-info/WHEEL
henge-0.2.2.dist-info/entry_points.txt
henge-0.2.2.dist-info/top_level.txt
henge-0.2.2.dist-info/RECORD
