Metadata-Version: 2.1
Name: henge
Version: 0.2.2
Summary: Storage and retrieval of object-derived, decomposable recursive unique identifiers.
Home-page: https://databio.org
Author: Nathan Sheffield
Author-email: nathan@code.databio.org
License: BSD2
Classifier: Development Status :: 4 - Beta
Classifier: License :: OSI Approved :: BSD License
Classifier: Programming Language :: Python :: 3.7
Classifier: Programming Language :: Python :: 3.8
Classifier: Programming Language :: Python :: 3.9
Classifier: Programming Language :: Python :: 3.10
Classifier: Topic :: System :: Distributed Computing
License-File: LICENSE.txt
Requires-Dist: jsonschema
Requires-Dist: ubiquerg >=0.5.2
Requires-Dist: yacman >=0.6.7
